spci/__init__.py
spci/getmusic.py
spci/mp.py
spci_sonic_pulse-2.1.3.dist-info/licenses/LICENSE
spci_sonic_pulse-2.1.3.dist-info/METADATA
spci_sonic_pulse-2.1.3.dist-info/WHEEL
spci_sonic_pulse-2.1.3.dist-info/entry_points.txt
spci_sonic_pulse-2.1.3.dist-info/top_level.txt
spci_sonic_pulse-2.1.3.dist-info/RECORD
