Metadata-Version: 2.4
Name: spci-sonic-pulse
Version: 2.1.3
Summary: A CLI music player with YouTube streaming and offline support
License: MIT
Project-URL: Repository, https://github.com/ojaswi1234/music_player_cli.git
Project-URL: Issues, https://github.com/ojaswi1234/music_player_cli/issues
Keywords: music-player,cli,terminal,youtube,audio,rich-ui,sonic-pulse
Classifier: Programming Language :: Python :: 3
Classifier: License :: OSI Approved :: MIT License
Classifier: Operating System :: OS Independent
Classifier: Topic :: Multimedia :: Sound/Audio :: Players
Classifier: Environment :: Console
Classifier: Intended Audience :: End Users/Desktop
Classifier: Development Status :: 5 - Production/Stable
Requires-Python: >=3.8
License-File: LICENSE
Requires-Dist: typer
Requires-Dist: rich
Requires-Dist: requests
Requires-Dist: yt-dlp
Requires-Dist: ytmusicapi
Requires-Dist: tinydb
Dynamic: license-file
